[
  {
    "id": "book-logicomix-an-epic-search-for-truth",
    "title": "Logicomix: An Epic Search for Truth",
    "date": "2013-12-01",
    "slug": "book-logicomix-an-epic-search-for-truth",
    "book_status": "rated",
    "original_source": "Goodreads",
    "book_author": "Apostolos Doxiadis",
    "goodreads_book_id": "6493321",
    "goodreads_rating": "3",
    "goodreads_exclusive_shelf": "read",
    "goodreads_date_read": "2013-12-01",
    "goodreads_date_added": "2013-12-30",
    "goodreads_isbn": "1596914521",
    "goodreads_isbn13": "9781596914520",
    "goodreads_publisher": "Bloomsbury (NYC)",
    "goodreads_binding": "Paperback",
    "goodreads_pages": "347",
    "goodreads_publication_year": "2009",
    "goodreads_original_publication_year": "2009"
  },
  {
    "id": "book-uncle-petros-and-goldbach-s-conjecture",
    "title": "Uncle Petros and Goldbach's Conjecture",
    "date": "2013-12-01",
    "slug": "book-uncle-petros-and-goldbach-s-conjecture",
    "book_status": "rated",
    "original_source": "Goodreads",
    "book_author": "Apostolos Doxiadis",
    "goodreads_book_id": "183015",
    "goodreads_rating": "4",
    "goodreads_exclusive_shelf": "read",
    "goodreads_date_read": "2013-12-01",
    "goodreads_date_added": "2013-12-30",
    "goodreads_isbn": "1582341281",
    "goodreads_isbn13": "9781582341286",
    "goodreads_publisher": "Bloomsbury USA",
    "goodreads_binding": "Mass Market Paperback",
    "goodreads_pages": "209",
    "goodreads_publication_year": "2001",
    "goodreads_original_publication_year": "1992"
  },
  {
    "id": "book-the-stranger",
    "title": "The Stranger",
    "date": "2014-01-01",
    "slug": "book-the-stranger",
    "book_status": "rated",
    "original_source": "Goodreads",
    "book_author": "Albert Camus",
    "goodreads_book_id": "49552",
    "goodreads_rating": "4",
    "goodreads_exclusive_shelf": "read",
    "goodreads_date_read": "2014-01-01",
    "goodreads_date_added": "2013-12-30",
    "goodreads_publisher": "Vintage International",
    "goodreads_binding": "Paperback",
    "goodreads_pages": "123",
    "goodreads_publication_year": "1989",
    "goodreads_original_publication_year": "1942"
  },
  {
    "id": "book-the-great-gatsby",
    "title": "The Great Gatsby",
    "date": "2014-01-03",
    "slug": "book-the-great-gatsby",
    "book_status": "rated",
    "original_source": "Goodreads",
    "book_author": "F. Scott Fitzgerald",
    "goodreads_book_id": "4671",
    "goodreads_rating": "3",
    "goodreads_exclusive_shelf": "read",
    "goodreads_date_read": "2014-01-03",
    "goodreads_date_added": "2014-01-01",
    "goodreads_isbn": "0743273567",
    "goodreads_isbn13": "9780743273565",
    "goodreads_publisher": "Scribner",
    "goodreads_binding": "Paperback",
    "goodreads_pages": "180",
    "goodreads_publication_year": "1925",
    "goodreads_original_publication_year": "1925"
  },
  {
    "id": "book-kane-abel",
    "title": "Kane \u0026 Abel (Kane \u0026 Abel, #1)",
    "date": "2014-04-01",
    "slug": "book-kane-abel",
    "book_status": "rated",
    "original_source": "Goodreads",
    "book_author": "Jeffrey Archer",
    "goodreads_book_id": "78983",
    "goodreads_rating": "4",
    "goodreads_exclusive_shelf": "read",
    "goodreads_date_read": "2014-04-01",
    "goodreads_date_added": "2014-06-01",
    "goodreads_isbn": "0312995059",
    "goodreads_isbn13": "9780312995058",
    "goodreads_publisher": "St. Martin's Paperbacks",
    "goodreads_binding": "Paperback",
    "goodreads_pages": "592",
    "goodreads_publication_year": "2004",
    "goodreads_original_publication_year": "1979"
  },
  {
    "id": "book-of-mice-and-men",
    "title": "Of Mice and Men",
    "date": "2014-04-01",
    "slug": "book-of-mice-and-men",
    "book_status": "rated",
    "original_source": "Goodreads",
    "book_author": "John Steinbeck",
    "goodreads_book_id": "890",
    "goodreads_rating": "3",
    "goodreads_exclusive_shelf": "read",
    "goodreads_date_read": "2014-04-01",
    "goodreads_date_added": "2014-01-03",
    "goodreads_isbn": "0142000671",
    "goodreads_isbn13": "9780142000670",
    "goodreads_publisher": "Penguin Books",
    "goodreads_binding": "Paperback",
    "goodreads_pages": "107",
    "goodreads_publication_year": "2002",
    "goodreads_original_publication_year": "1937"
  },
  {
    "id": "book-1984",
    "title": "1984",
    "date": "2014-07-01",
    "slug": "book-1984",
    "book_status": "rated",
    "original_source": "Goodreads",
    "book_author": "George Orwell",
    "goodreads_book_id": "5470",
    "goodreads_rating": "3",
    "goodreads_exclusive_shelf": "read",
    "goodreads_date_read": "2014-07-01",
    "goodreads_date_added": "2014-07-01",
    "goodreads_publisher": "New American Library",
    "goodreads_binding": "Mass Market Paperback",
    "goodreads_pages": "328",
    "goodreads_publication_year": "1950",
    "goodreads_original_publication_year": "1948"
  },
  {
    "id": "book-animal-farm",
    "title": "Animal Farm",
    "date": "2014-07-01",
    "slug": "book-animal-farm",
    "book_status": "rated",
    "original_source": "Goodreads",
    "book_author": "George Orwell",
    "goodreads_book_id": "7613",
    "goodreads_rating": "5",
    "goodreads_exclusive_shelf": "read",
    "goodreads_date_read": "2014-07-01",
    "goodreads_date_added": "2014-07-01",
    "goodreads_publisher": "Plume",
    "goodreads_binding": "Paperback",
    "goodreads_pages": "129",
    "goodreads_publication_year": "2003",
    "goodreads_original_publication_year": "1945"
  },
  {
    "id": "book-deception-point",
    "title": "Deception Point",
    "date": "2014-07-03",
    "slug": "book-deception-point",
    "book_status": "rated",
    "original_source": "Goodreads",
    "book_author": "Dan    Brown",
    "goodreads_book_id": "976",
    "goodreads_rating": "2",
    "goodreads_exclusive_shelf": "read",
    "goodreads_date_added": "2014-07-03",
    "goodreads_isbn": "0671027387",
    "goodreads_isbn13": "9780671027384",
    "goodreads_publisher": "Pocket Books",
    "goodreads_binding": "Paperback",
    "goodreads_pages": "556",
    "goodreads_publication_year": "2002",
    "goodreads_original_publication_year": "2001"
  },
  {
    "id": "book-the-da-vinci-code",
    "title": "The Da Vinci Code (Robert Langdon, #2)",
    "date": "2014-07-03",
    "slug": "book-the-da-vinci-code",
    "book_status": "rated",
    "original_source": "Goodreads",
    "book_author": "Dan    Brown",
    "goodreads_book_id": "968",
    "goodreads_rating": "3",
    "goodreads_exclusive_shelf": "read",
    "goodreads_date_added": "2014-07-03",
    "goodreads_publisher": "Anchor",
    "goodreads_binding": "Paperback",
    "goodreads_pages": "489",
    "goodreads_publication_year": "2006",
    "goodreads_original_publication_year": "2003"
  },
  {
    "id": "book-the-lost-symbol",
    "title": "The Lost Symbol (Robert Langdon, #3)",
    "date": "2014-07-03",
    "slug": "book-the-lost-symbol",
    "book_status": "rated",
    "original_source": "Goodreads",
    "book_author": "Dan    Brown",
    "goodreads_book_id": "6411961",
    "goodreads_rating": "1",
    "goodreads_exclusive_shelf": "read",
    "goodreads_date_added": "2014-07-03",
    "goodreads_isbn": "0385504225",
    "goodreads_isbn13": "9780385504225",
    "goodreads_publisher": "Doubleday",
    "goodreads_binding": "Hardcover",
    "goodreads_pages": "509",
    "goodreads_publication_year": "2009",
    "goodreads_original_publication_year": "2009"
  },
  {
    "id": "book-the-spy-who-came-in-from-the-cold",
    "title": "The Spy Who Came In from the Cold (George Smiley, #3)",
    "date": "2014-07-03",
    "slug": "book-the-spy-who-came-in-from-the-cold",
    "book_status": "rated",
    "original_source": "Goodreads",
    "book_author": "John le Carré",
    "goodreads_book_id": "19494",
    "goodreads_rating": "4",
    "goodreads_exclusive_shelf": "read",
    "goodreads_date_read": "2014-07-03",
    "goodreads_date_added": "2014-07-03",
    "goodreads_isbn13": "9780743442534",
    "goodreads_publisher": "Scribner",
    "goodreads_binding": "Paperback",
    "goodreads_pages": "212",
    "goodreads_publication_year": "2001",
    "goodreads_original_publication_year": "1963"
  },
  {
    "id": "book-wild-from-lost-to-found-on-the-pacific-crest-trail",
    "title": "Wild: From Lost to Found on the Pacific Crest Trail",
    "date": "2014-07-08",
    "slug": "book-wild-from-lost-to-found-on-the-pacific-crest-trail",
    "book_status": "rated",
    "original_source": "Goodreads",
    "book_author": "Cheryl Strayed",
    "goodreads_book_id": "12262741",
    "goodreads_rating": "3",
    "goodreads_exclusive_shelf": "read",
    "goodreads_date_read": "2014-07-08",
    "goodreads_date_added": "2014-07-06",
    "goodreads_isbn": "0307592731",
    "goodreads_isbn13": "9780307592736",
    "goodreads_publisher": "Knopf",
    "goodreads_binding": "Hardcover",
    "goodreads_pages": "336",
    "goodreads_publication_year": "2012",
    "goodreads_original_publication_year": "2012"
  },
  {
    "id": "book-lean-in-women-work-and-the-will-to-lead",
    "title": "Lean In: Women, Work, and the Will to Lead",
    "date": "2014-07-16",
    "slug": "book-lean-in-women-work-and-the-will-to-lead",
    "book_status": "rated",
    "original_source": "Goodreads",
    "book_author": "Sheryl Sandberg",
    "goodreads_book_id": "16071764",
    "goodreads_rating": "5",
    "goodreads_exclusive_shelf": "read",
    "goodreads_date_read": "2014-07-16",
    "goodreads_date_added": "2014-07-03",
    "goodreads_isbn": "0385349947",
    "goodreads_isbn13": "9780385349949",
    "goodreads_publisher": "Knopf",
    "goodreads_binding": "Hardcover",
    "goodreads_pages": "217",
    "goodreads_publication_year": "2013"
  },
  {
    "id": "book-the-catcher-in-the-rye",
    "title": "The Catcher in the Rye",
    "date": "2014-07-20",
    "slug": "book-the-catcher-in-the-rye",
    "book_status": "rated",
    "original_source": "Goodreads",
    "book_author": "J.D. Salinger",
    "goodreads_book_id": "5107",
    "goodreads_rating": "5",
    "goodreads_exclusive_shelf": "read",
    "goodreads_date_read": "2014-07-20",
    "goodreads_date_added": "2014-07-19",
    "goodreads_isbn": "0316769177",
    "goodreads_isbn13": "9780316769174",
    "goodreads_publisher": "Back Bay Books",
    "goodreads_binding": "Paperback",
    "goodreads_pages": "277",
    "goodreads_publication_year": "2001",
    "goodreads_original_publication_year": "1951"
  },
  {
    "id": "book-the-importance-of-being-earnest",
    "title": "The Importance of Being Earnest",
    "date": "2014-07-26",
    "slug": "book-the-importance-of-being-earnest",
    "book_status": "rated",
    "original_source": "Goodreads",
    "book_author": "Oscar Wilde",
    "goodreads_book_id": "92303",
    "goodreads_rating": "3",
    "goodreads_exclusive_shelf": "read",
    "goodreads_date_read": "2014-07-26",
    "goodreads_date_added": "2014-07-25",
    "goodreads_isbn": "158049580X",
    "goodreads_isbn13": "9781580495806",
    "goodreads_publisher": "Prestwick House",
    "goodreads_binding": "Paperback",
    "goodreads_pages": "89",
    "goodreads_publication_year": "2005",
    "goodreads_original_publication_year": "1895"
  },
  {
    "id": "book-the-kite-runner",
    "title": "The Kite Runner",
    "date": "2014-08-02",
    "slug": "book-the-kite-runner",
    "book_status": "rated",
    "original_source": "Goodreads",
    "book_author": "Khaled Hosseini",
    "goodreads_book_id": "77203",
    "goodreads_rating": "5",
    "goodreads_exclusive_shelf": "read",
    "goodreads_date_read": "2014-08-02",
    "goodreads_date_added": "2014-07-27",
    "goodreads_isbn": "159463193X",
    "goodreads_isbn13": "9781594631931",
    "goodreads_publisher": "Riverhead Books",
    "goodreads_binding": "Paperback",
    "goodreads_pages": "371",
    "goodreads_publication_year": "2004",
    "goodreads_original_publication_year": "2003"
  },
  {
    "id": "book-the-giver",
    "title": "The Giver (The Giver, #1)",
    "date": "2014-08-16",
    "slug": "book-the-giver",
    "book_status": "rated",
    "original_source": "Goodreads",
    "book_author": "Lois Lowry",
    "goodreads_book_id": "3636",
    "goodreads_rating": "4",
    "goodreads_exclusive_shelf": "read",
    "goodreads_date_read": "2014-08-16",
    "goodreads_date_added": "2014-07-29",
    "goodreads_isbn": "0385732554",
    "goodreads_isbn13": "9780385732550",
    "goodreads_publisher": "Ember",
    "goodreads_binding": "Paperback",
    "goodreads_pages": "208",
    "goodreads_publication_year": "2006",
    "goodreads_original_publication_year": "1993"
  },
  {
    "id": "book-a-thousand-splendid-suns",
    "title": "A Thousand Splendid Suns",
    "date": "2014-09-11",
    "slug": "book-a-thousand-splendid-suns",
    "book_status": "rated",
    "original_source": "Goodreads",
    "book_author": "Khaled Hosseini",
    "goodreads_book_id": "128029",
    "goodreads_rating": "5",
    "goodreads_exclusive_shelf": "read",
    "goodreads_date_read": "2014-09-11",
    "goodreads_date_added": "2014-09-11",
    "goodreads_isbn": "1594489505",
    "goodreads_isbn13": "9781594489501",
    "goodreads_publisher": "Riverhead Books",
    "goodreads_binding": "Hardcover",
    "goodreads_pages": "372",
    "goodreads_publication_year": "2007",
    "goodreads_original_publication_year": "2007"
  },
  {
    "id": "book-choke",
    "title": "Choke",
    "date": "2014-10-02",
    "slug": "book-choke",
    "book_status": "rated",
    "original_source": "Goodreads",
    "book_author": "Chuck Palahniuk",
    "goodreads_book_id": "29059",
    "goodreads_rating": "5",
    "goodreads_exclusive_shelf": "read",
    "goodreads_date_added": "2014-10-02",
    "goodreads_isbn": "0385720920",
    "goodreads_isbn13": "9780385720922",
    "goodreads_publisher": "Anchor Books",
    "goodreads_binding": "Paperback",
    "goodreads_pages": "293",
    "goodreads_publication_year": "2002",
    "goodreads_original_publication_year": "2001"
  },
  {
    "id": "book-coraline",
    "title": "Coraline",
    "date": "2014-10-03",
    "slug": "book-coraline",
    "book_status": "rated",
    "original_source": "Goodreads",
    "book_author": "Neil Gaiman",
    "goodreads_book_id": "17061",
    "goodreads_rating": "2",
    "goodreads_exclusive_shelf": "read",
    "goodreads_date_added": "2014-10-03",
    "goodreads_isbn": "0061139378",
    "goodreads_isbn13": "9780061139376",
    "goodreads_publisher": "William Morrow Paperbacks",
    "goodreads_binding": "Paperback",
    "goodreads_pages": "208",
    "goodreads_publication_year": "2006",
    "goodreads_original_publication_year": "2002"
  },
  {
    "id": "book-i-am-legend",
    "title": "I Am Legend",
    "date": "2014-10-08",
    "slug": "book-i-am-legend",
    "book_status": "rated",
    "original_source": "Goodreads",
    "book_author": "Richard Matheson",
    "goodreads_book_id": "14064",
    "goodreads_rating": "5",
    "goodreads_exclusive_shelf": "read",
    "goodreads_date_read": "2014-10-08",
    "goodreads_date_added": "2014-10-06",
    "goodreads_isbn": "1857988094",
    "goodreads_isbn13": "9781857988093",
    "goodreads_publisher": "Millennium",
    "goodreads_binding": "Paperback",
    "goodreads_pages": "160",
    "goodreads_publication_year": "1999",
    "goodreads_original_publication_year": "1954"
  },
  {
    "id": "book-childhood-s-end",
    "title": "Childhood’s End",
    "date": "2014-10-21",
    "slug": "book-childhood-s-end",
    "book_status": "rated",
    "original_source": "Goodreads",
    "book_author": "Arthur C. Clarke",
    "goodreads_book_id": "414999",
    "goodreads_rating": "3",
    "goodreads_exclusive_shelf": "read",
    "goodreads_date_added": "2014-10-21",
    "goodreads_publisher": "Del Rey Books",
    "goodreads_binding": "Mass Market Paperback",
    "goodreads_pages": "224",
    "goodreads_publication_year": "1987",
    "goodreads_original_publication_year": "1953"
  },
  {
    "id": "book-ender-s-game",
    "title": "Ender’s Game (Ender's Saga, #1)",
    "date": "2014-10-25",
    "slug": "book-ender-s-game",
    "book_status": "rated",
    "original_source": "Goodreads",
    "book_author": "Orson Scott Card",
    "goodreads_book_id": "375802",
    "goodreads_rating": "4",
    "goodreads_exclusive_shelf": "read",
    "goodreads_date_read": "2014-10-25",
    "goodreads_date_added": "2014-07-29",
    "goodreads_isbn": "0812550706",
    "goodreads_isbn13": "9780812550702",
    "goodreads_publisher": "Tor",
    "goodreads_binding": "Mass Market Paperback",
    "goodreads_pages": "324",
    "goodreads_publication_year": "2004",
    "goodreads_original_publication_year": "1985"
  },
  {
    "id": "book-the-hit",
    "title": "The Hit (Will Robie, #2)",
    "date": "2014-10-25",
    "slug": "book-the-hit",
    "book_status": "rated",
    "original_source": "Goodreads",
    "book_author": "David Baldacci",
    "goodreads_book_id": "15791154",
    "goodreads_rating": "3",
    "goodreads_exclusive_shelf": "read",
    "goodreads_date_added": "2014-10-25",
    "goodreads_isbn": "1455521213",
    "goodreads_isbn13": "9781455521210",
    "goodreads_publisher": "Grand Central Publishing",
    "goodreads_binding": "Hardcover",
    "goodreads_pages": "392",
    "goodreads_publication_year": "2013",
    "goodreads_original_publication_year": "2013"
  },
  {
    "id": "book-stranger-in-a-strange-land",
    "title": "Stranger in a Strange Land",
    "date": "2014-11-08",
    "slug": "book-stranger-in-a-strange-land",
    "book_status": "rated",
    "original_source": "Goodreads",
    "book_author": "Robert A. Heinlein",
    "goodreads_book_id": "350",
    "goodreads_rating": "3",
    "goodreads_exclusive_shelf": "read",
    "goodreads_date_read": "2014-11-08",
    "goodreads_date_added": "2014-10-21",
    "goodreads_publisher": "Ace",
    "goodreads_binding": "Paperback",
    "goodreads_pages": "525",
    "goodreads_publication_year": "1991",
    "goodreads_original_publication_year": "1961"
  },
  {
    "id": "book-a-week-at-the-airport-a-heathrow-diary",
    "title": "A Week at the Airport: A Heathrow Diary",
    "date": "2014-11-09",
    "slug": "book-a-week-at-the-airport-a-heathrow-diary",
    "book_status": "rated",
    "original_source": "Goodreads",
    "book_author": "Alain de Botton",
    "goodreads_book_id": "6718808",
    "goodreads_rating": "5",
    "goodreads_exclusive_shelf": "read",
    "goodreads_date_added": "2014-11-09",
    "goodreads_isbn": "1846683599",
    "goodreads_isbn13": "9781846683596",
    "goodreads_publisher": "Profile Books",
    "goodreads_binding": "Paperback",
    "goodreads_pages": "112",
    "goodreads_publication_year": "2010",
    "goodreads_original_publication_year": "2009"
  },
  {
    "id": "book-the-curious-incident-of-the-dog-in-the-night-time",
    "title": "The Curious Incident of the Dog in the Night-Time",
    "date": "2014-11-21",
    "slug": "book-the-curious-incident-of-the-dog-in-the-night-time",
    "book_status": "rated",
    "original_source": "Goodreads",
    "book_author": "Mark Haddon",
    "goodreads_book_id": "1618",
    "goodreads_rating": "2",
    "goodreads_exclusive_shelf": "read",
    "goodreads_date_added": "2014-11-21",
    "goodreads_isbn": "1400032717",
    "goodreads_isbn13": "9781400032716",
    "goodreads_publisher": "Vintage",
    "goodreads_binding": "Paperback",
    "goodreads_pages": "226",
    "goodreads_publication_year": "2004",
    "goodreads_original_publication_year": "2003"
  },
  {
    "id": "book-the-hobbit-or-there-and-back-again",
    "title": "The Hobbit, or There and Back Again",
    "date": "2014-12-11",
    "slug": "book-the-hobbit-or-there-and-back-again",
    "book_status": "rated",
    "original_source": "Goodreads",
    "book_author": "J.R.R. Tolkien",
    "goodreads_book_id": "5907",
    "goodreads_rating": "5",
    "goodreads_exclusive_shelf": "read",
    "goodreads_date_read": "2014-12-11",
    "goodreads_date_added": "2014-10-03",
    "goodreads_publisher": "Houghton Mifflin",
    "goodreads_binding": "Paperback",
    "goodreads_pages": "366",
    "goodreads_publication_year": "2002",
    "goodreads_original_publication_year": "1937"
  },
  {
    "id": "book-cat-s-cradle",
    "title": "Cat’s Cradle",
    "date": "2014-12-14",
    "slug": "book-cat-s-cradle",
    "book_status": "rated",
    "original_source": "Goodreads",
    "book_author": "Kurt Vonnegut Jr.",
    "goodreads_book_id": "135479",
    "goodreads_rating": "3",
    "goodreads_exclusive_shelf": "read",
    "goodreads_date_read": "2014-12-14",
    "goodreads_date_added": "2014-10-06",
    "goodreads_publisher": "Penguin",
    "goodreads_binding": "Paperback",
    "goodreads_pages": "306",
    "goodreads_publication_year": "1999",
    "goodreads_original_publication_year": "1963"
  },
  {
    "id": "book-anthem",
    "title": "Anthem",
    "date": "2014-12-17",
    "slug": "book-anthem",
    "book_status": "rated",
    "original_source": "Goodreads",
    "book_author": "Ayn Rand",
    "goodreads_book_id": "667",
    "goodreads_rating": "4",
    "goodreads_exclusive_shelf": "read",
    "goodreads_date_added": "2014-12-17",
    "goodreads_isbn": "0452281253",
    "goodreads_isbn13": "9780452281257",
    "goodreads_publisher": "NAL",
    "goodreads_binding": "Paperback",
    "goodreads_pages": "105",
    "goodreads_publication_year": "1999",
    "goodreads_original_publication_year": "1938"
  },
  {
    "id": "book-the-opposite-of-loneliness-essays-and-stories",
    "title": "The Opposite of Loneliness: Essays and Stories",
    "date": "2014-12-27",
    "slug": "book-the-opposite-of-loneliness-essays-and-stories",
    "book_status": "rated",
    "original_source": "Goodreads",
    "book_author": "Marina Keegan",
    "goodreads_book_id": "18143905",
    "goodreads_rating": "4",
    "goodreads_exclusive_shelf": "read",
    "goodreads_date_read": "2014-12-27",
    "goodreads_date_added": "2014-12-14",
    "goodreads_isbn": "147675361X",
    "goodreads_isbn13": "9781476753614",
    "goodreads_publisher": "Scribner",
    "goodreads_binding": "Hardcover",
    "goodreads_pages": "208",
    "goodreads_publication_year": "2014",
    "goodreads_original_publication_year": "2014"
  },
  {
    "id": "book-and-to-think-that-i-saw-it-on-mulberry-street",
    "title": "And to Think That I Saw It on Mulberry Street",
    "date": "2014-12-31",
    "slug": "book-and-to-think-that-i-saw-it-on-mulberry-street",
    "book_status": "rated",
    "original_source": "Goodreads",
    "book_author": "Dr. Seuss",
    "goodreads_book_id": "28351",
    "goodreads_rating": "4",
    "goodreads_exclusive_shelf": "read",
    "goodreads_date_read": "2014-12-31",
    "goodreads_date_added": "2014-12-31",
    "goodreads_isbn": "0007169922",
    "goodreads_isbn13": "9780007169924",
    "goodreads_publisher": "HarperCollinsChildren’sBooks",
    "goodreads_binding": "Paperback",
    "goodreads_pages": "64",
    "goodreads_publication_year": "2003",
    "goodreads_original_publication_year": "1937"
  },
  {
    "id": "book-the-notebook",
    "title": "The Notebook (The Notebook, #1)",
    "date": "2014-12-31",
    "slug": "book-the-notebook",
    "book_status": "rated",
    "original_source": "Goodreads",
    "book_author": "Nicholas Sparks",
    "goodreads_book_id": "15931",
    "goodreads_rating": "3",
    "goodreads_exclusive_shelf": "read",
    "goodreads_date_read": "2014-12-31",
    "goodreads_date_added": "2014-12-31",
    "goodreads_isbn": "0553816713",
    "goodreads_isbn13": "9780553816716",
    "goodreads_publisher": "Bantam",
    "goodreads_binding": "Hardcover",
    "goodreads_pages": "214",
    "goodreads_publication_year": "2004",
    "goodreads_original_publication_year": "1996"
  },
  {
    "id": "book-weirdos-from-another-planet",
    "title": "Weirdos from Another Planet! (Calvin and Hobbes, #4)",
    "date": "2014-12-31",
    "slug": "book-weirdos-from-another-planet",
    "book_status": "rated",
    "original_source": "Goodreads",
    "book_author": "Bill Watterson",
    "goodreads_book_id": "77730",
    "goodreads_rating": "5",
    "goodreads_exclusive_shelf": "read",
    "goodreads_date_added": "2014-12-31",
    "goodreads_isbn": "0836218620",
    "goodreads_isbn13": "9780439137492",
    "goodreads_publisher": "Andrews and McMeel Publishing",
    "goodreads_binding": "Paperback",
    "goodreads_pages": "128",
    "goodreads_publication_year": "1990",
    "goodreads_original_publication_year": "1990"
  },
  {
    "id": "book-flowers-for-algernon",
    "title": "Flowers for Algernon",
    "date": "2015-01-02",
    "slug": "book-flowers-for-algernon",
    "book_status": "rated",
    "original_source": "Goodreads",
    "book_author": "Daniel Keyes",
    "goodreads_book_id": "18373",
    "goodreads_rating": "5",
    "goodreads_exclusive_shelf": "read",
    "goodreads_date_read": "2015-01-02",
    "goodreads_date_added": "2014-11-06",
    "goodreads_isbn": "015603008X",
    "goodreads_isbn13": "9780156030083",
    "goodreads_publisher": "Harvest Books",
    "goodreads_binding": "Paperback",
    "goodreads_pages": "311",
    "goodreads_publication_year": "2004",
    "goodreads_original_publication_year": "1966"
  },
  {
    "id": "book-the-martian",
    "title": "The Martian",
    "date": "2015-01-10",
    "slug": "book-the-martian",
    "book_status": "rated",
    "original_source": "Goodreads",
    "book_author": "Andy Weir",
    "goodreads_book_id": "18007564",
    "goodreads_rating": "5",
    "goodreads_exclusive_shelf": "read",
    "goodreads_date_read": "2015-01-10",
    "goodreads_date_added": "2014-12-15",
    "goodreads_isbn": "0804139024",
    "goodreads_isbn13": "9780804139021",
    "goodreads_publisher": "Crown Publishers",
    "goodreads_binding": "Hardcover",
    "goodreads_pages": "369",
    "goodreads_publication_year": "2014",
    "goodreads_original_publication_year": "2011"
  },
  {
    "id": "book-the-game-penetrating-the-secret-society-of-pickup-artists",
    "title": "The Game: Penetrating the Secret Society of Pickup Artists",
    "date": "2015-01-13",
    "slug": "book-the-game-penetrating-the-secret-society-of-pickup-artists",
    "book_status": "rated",
    "original_source": "Goodreads",
    "book_author": "Neil Strauss",
    "goodreads_book_id": "900",
    "goodreads_rating": "3",
    "goodreads_exclusive_shelf": "read",
    "goodreads_date_read": "2015-01-13",
    "goodreads_date_added": "2015-01-12",
    "goodreads_isbn": "0060554738",
    "goodreads_isbn13": "9780060554736",
    "goodreads_publisher": "It Books",
    "goodreads_binding": "Hardcover",
    "goodreads_pages": "464",
    "goodreads_publication_year": "2005",
    "goodreads_original_publication_year": "2005"
  },
  {
    "id": "book-the-psychopath-test-a-journey-through-the-madness-industry",
    "title": "The Psychopath Test: A Journey Through the Madness Industry",
    "date": "2015-02-21",
    "slug": "book-the-psychopath-test-a-journey-through-the-madness-industry",
    "book_status": "rated",
    "original_source": "Goodreads",
    "book_author": "Jon Ronson",
    "goodreads_book_id": "12391521",
    "goodreads_rating": "3",
    "goodreads_exclusive_shelf": "read",
    "goodreads_date_read": "2015-02-21",
    "goodreads_date_added": "2014-11-06",
    "goodreads_isbn": "1594485755",
    "goodreads_isbn13": "9781594485756",
    "goodreads_publisher": "Riverhead Books",
    "goodreads_binding": "Paperback",
    "goodreads_pages": "275",
    "goodreads_publication_year": "2012",
    "goodreads_original_publication_year": "2011"
  },
  {
    "id": "book-mr-mercedes",
    "title": "Mr. Mercedes (Bill Hodges #1)",
    "date": "2015-03-31",
    "slug": "book-mr-mercedes",
    "book_status": "rated",
    "original_source": "Goodreads",
    "book_author": "Stephen  King",
    "goodreads_book_id": "18775247",
    "goodreads_rating": "2",
    "goodreads_exclusive_shelf": "read",
    "goodreads_date_read": "2015-03-31",
    "goodreads_date_added": "2015-03-23",
    "goodreads_isbn": "1476754454",
    "goodreads_isbn13": "9781476754451",
    "goodreads_publisher": "Scribner",
    "goodreads_binding": "Hardcover",
    "goodreads_pages": "437",
    "goodreads_publication_year": "2014",
    "goodreads_original_publication_year": "2014"
  },
  {
    "id": "book-2001-a-space-odyssey",
    "title": "2001: A Space Odyssey (Space Odyssey, #1)",
    "date": "2015-05-25",
    "slug": "book-2001-a-space-odyssey",
    "book_status": "rated",
    "original_source": "Goodreads",
    "book_author": "Arthur C. Clarke",
    "goodreads_book_id": "70535",
    "goodreads_rating": "3",
    "goodreads_exclusive_shelf": "read",
    "goodreads_date_read": "2015-05-25",
    "goodreads_date_added": "2015-05-22",
    "goodreads_publisher": "Roc",
    "goodreads_binding": "Paperback",
    "goodreads_pages": "297",
    "goodreads_publication_year": "2000",
    "goodreads_original_publication_year": "1968"
  },
  {
    "id": "book-johnny-got-his-gun",
    "title": "Johnny Got His Gun",
    "date": "2015-07-04",
    "slug": "book-johnny-got-his-gun",
    "book_status": "rated",
    "original_source": "Goodreads",
    "book_author": "Dalton Trumbo",
    "goodreads_book_id": "51606",
    "goodreads_rating": "4",
    "goodreads_exclusive_shelf": "read",
    "goodreads_date_read": "2015-07-04",
    "goodreads_date_added": "2014-11-06",
    "goodreads_isbn": "0806512814",
    "goodreads_isbn13": "9780806512815",
    "goodreads_publisher": "Citadel",
    "goodreads_binding": "Paperback",
    "goodreads_pages": "309",
    "goodreads_publication_year": "1998",
    "goodreads_original_publication_year": "1939"
  },
  {
    "id": "book-ready-player-one",
    "title": "Ready Player One (Ready Player One, #1)",
    "date": "2015-07-10",
    "slug": "book-ready-player-one",
    "book_status": "rated",
    "original_source": "Goodreads",
    "book_author": "Ernest Cline",
    "goodreads_book_id": "9969571",
    "goodreads_rating": "4",
    "goodreads_exclusive_shelf": "read",
    "goodreads_date_read": "2015-07-10",
    "goodreads_date_added": "2015-01-13",
    "goodreads_isbn": "030788743X",
    "goodreads_isbn13": "9780307887436",
    "goodreads_publisher": "Crown Publishers",
    "goodreads_binding": "Hardcover",
    "goodreads_pages": "480",
    "goodreads_publication_year": "2011",
    "goodreads_original_publication_year": "2011"
  },
  {
    "id": "book-the-art-of-racing-in-the-rain",
    "title": "The Art of Racing in the Rain",
    "date": "2015-07-10",
    "slug": "book-the-art-of-racing-in-the-rain",
    "book_status": "rated",
    "original_source": "Goodreads",
    "book_author": "Garth Stein",
    "goodreads_book_id": "3153910",
    "goodreads_rating": "5",
    "goodreads_exclusive_shelf": "read",
    "goodreads_date_added": "2015-07-10",
    "goodreads_isbn": "1554681723",
    "goodreads_isbn13": "9781554681723",
    "goodreads_publisher": "Harper Collins",
    "goodreads_binding": "Hardcover",
    "goodreads_pages": "336",
    "goodreads_publication_year": "2008",
    "goodreads_original_publication_year": "2008"
  },
  {
    "id": "book-are-you-there-vodka-it-s-me-chelsea",
    "title": "Are You There, Vodka? It's Me, Chelsea",
    "date": "2015-07-28",
    "slug": "book-are-you-there-vodka-it-s-me-chelsea",
    "book_status": "rated",
    "original_source": "Goodreads",
    "book_author": "Chelsea Handler",
    "goodreads_book_id": "40173",
    "goodreads_rating": "2",
    "goodreads_exclusive_shelf": "read",
    "goodreads_date_read": "2015-07-28",
    "goodreads_date_added": "2015-07-28",
    "goodreads_isbn": "0061173398",
    "goodreads_isbn13": "9780061173394",
    "goodreads_publisher": "Simon Spotlight Entertainment",
    "goodreads_binding": "Hardcover",
    "goodreads_pages": "264",
    "goodreads_publication_year": "2008",
    "goodreads_original_publication_year": "2008"
  },
  {
    "id": "book-old-school",
    "title": "Old School",
    "date": "2015-12-10",
    "slug": "book-old-school",
    "book_status": "rated",
    "original_source": "Goodreads",
    "book_author": "Tobias Wolff",
    "goodreads_book_id": "11464",
    "goodreads_rating": "5",
    "goodreads_exclusive_shelf": "read",
    "goodreads_date_read": "2015-12-10",
    "goodreads_date_added": "2015-12-08",
    "goodreads_isbn": "0747574650",
    "goodreads_isbn13": "9780747574651",
    "goodreads_publisher": "Bloomsbury",
    "goodreads_binding": "Paperback",
    "goodreads_pages": "196",
    "goodreads_publication_year": "2005",
    "goodreads_original_publication_year": "2003"
  },
  {
    "id": "book-the-god-of-small-things",
    "title": "The God of Small Things",
    "date": "2016-01-01",
    "slug": "book-the-god-of-small-things",
    "book_status": "rated",
    "original_source": "Goodreads",
    "book_author": "Arundhati Roy",
    "goodreads_book_id": "9777",
    "goodreads_rating": "4",
    "goodreads_exclusive_shelf": "read",
    "goodreads_date_read": "2016-01-01",
    "goodreads_date_added": "2015-01-13",
    "goodreads_isbn": "0679457313",
    "goodreads_isbn13": "9780679457312",
    "goodreads_publisher": "Random House",
    "goodreads_binding": "Paperback",
    "goodreads_pages": "321",
    "goodreads_publication_year": "1997",
    "goodreads_original_publication_year": "1997"
  },
  {
    "id": "book-women",
    "title": "Women",
    "date": "2016-02-15",
    "slug": "book-women",
    "book_status": "rated",
    "original_source": "Goodreads",
    "book_author": "Charles Bukowski",
    "goodreads_book_id": "38500",
    "goodreads_rating": "2",
    "goodreads_exclusive_shelf": "read",
    "goodreads_date_added": "2016-02-15",
    "goodreads_isbn": "0061177598",
    "goodreads_isbn13": "9780061177590",
    "goodreads_publisher": "Ecco",
    "goodreads_binding": "Paperback",
    "goodreads_pages": "291",
    "goodreads_publication_year": "2007",
    "goodreads_original_publication_year": "1978"
  },
  {
    "id": "book-how-i-became-a-famous-novelist",
    "title": "How I Became a Famous Novelist",
    "date": "2016-06-05",
    "slug": "book-how-i-became-a-famous-novelist",
    "book_status": "rated",
    "original_source": "Goodreads",
    "book_author": "Steve Hely",
    "goodreads_book_id": "6013046",
    "goodreads_rating": "3",
    "goodreads_exclusive_shelf": "read",
    "goodreads_date_read": "2016-06-05",
    "goodreads_date_added": "2016-06-05",
    "goodreads_isbn": "0802170609",
    "goodreads_isbn13": "9780802170606",
    "goodreads_publisher": "Grove Press, Black Cat",
    "goodreads_binding": "Paperback",
    "goodreads_pages": "322",
    "goodreads_publication_year": "2009",
    "goodreads_original_publication_year": "2009"
  },
  {
    "id": "book-when-breath-becomes-air",
    "title": "When Breath Becomes Air",
    "date": "2016-06-07",
    "slug": "book-when-breath-becomes-air",
    "book_status": "rated",
    "original_source": "Goodreads",
    "book_author": "Paul Kalanithi",
    "goodreads_book_id": "25899336",
    "goodreads_rating": "4",
    "goodreads_exclusive_shelf": "read",
    "goodreads_date_read": "2016-06-07",
    "goodreads_date_added": "2016-06-06",
    "goodreads_isbn": "0812988418",
    "goodreads_isbn13": "9780812988413",
    "goodreads_publisher": "Random House",
    "goodreads_binding": "Kindle Edition",
    "goodreads_pages": "208",
    "goodreads_publication_year": "2016",
    "goodreads_original_publication_year": "2016"
  },
  {
    "id": "book-the-death-of-ivan-ilych",
    "title": "The Death of Ivan Ilych",
    "date": "2016-06-09",
    "slug": "book-the-death-of-ivan-ilych",
    "book_status": "rated",
    "original_source": "Goodreads",
    "book_author": "Leo Tolstoy",
    "goodreads_book_id": "18386",
    "goodreads_rating": "4",
    "goodreads_exclusive_shelf": "read",
    "goodreads_date_read": "2016-06-09",
    "goodreads_date_added": "2016-06-07",
    "goodreads_publisher": "Waking Lion Press",
    "goodreads_binding": "Paperback",
    "goodreads_pages": "86",
    "goodreads_publication_year": "2006",
    "goodreads_original_publication_year": "1886"
  },
  {
    "id": "book-the-night-in-question",
    "title": "The Night in Question",
    "date": "2016-06-21",
    "slug": "book-the-night-in-question",
    "book_status": "rated",
    "original_source": "Goodreads",
    "book_author": "Tobias Wolff",
    "goodreads_book_id": "251374",
    "goodreads_rating": "5",
    "goodreads_exclusive_shelf": "read",
    "goodreads_date_added": "2016-06-21",
    "goodreads_isbn": "0679402187",
    "goodreads_isbn13": "9780679402183",
    "goodreads_publisher": "Knopf",
    "goodreads_binding": "Hardcover",
    "goodreads_pages": "206",
    "goodreads_publication_year": "1996",
    "goodreads_original_publication_year": "1995"
  },
  {
    "id": "book-fahrenheit-451",
    "title": "Fahrenheit 451",
    "date": "2016-06-22",
    "slug": "book-fahrenheit-451",
    "book_status": "rated",
    "original_source": "Goodreads",
    "book_author": "Ray Bradbury",
    "goodreads_book_id": "17470674",
    "goodreads_rating": "4",
    "goodreads_exclusive_shelf": "read",
    "goodreads_date_read": "2016-06-22",
    "goodreads_date_added": "2016-06-21",
    "goodreads_isbn": "0007491565",
    "goodreads_isbn13": "9780007491568",
    "goodreads_publisher": "Harper Voyager",
    "goodreads_binding": "Hardcover",
    "goodreads_pages": "227",
    "goodreads_publication_year": "2013",
    "goodreads_original_publication_year": "1953"
  },
  {
    "id": "book-the-count-of-monte-cristo",
    "title": "The Count of Monte Cristo",
    "date": "2016-12-18",
    "slug": "book-the-count-of-monte-cristo",
    "book_status": "rated",
    "original_source": "Goodreads",
    "book_author": "Alexandre Dumas",
    "goodreads_book_id": "7126",
    "goodreads_rating": "5",
    "goodreads_exclusive_shelf": "read",
    "goodreads_date_read": "2016-12-18",
    "goodreads_date_added": "2014-10-06",
    "goodreads_isbn": "0140449264",
    "goodreads_isbn13": "9780140449266",
    "goodreads_publisher": "Penguin Classics",
    "goodreads_binding": "Paperback",
    "goodreads_pages": "1276",
    "goodreads_publication_year": "2003",
    "goodreads_original_publication_year": "1844"
  },
  {
    "id": "book-frankenstein",
    "title": "Frankenstein",
    "date": "2016-12-21",
    "slug": "book-frankenstein",
    "book_status": "rated",
    "original_source": "Goodreads",
    "book_author": "Mary Wollstonecraft Shelley",
    "goodreads_book_id": "15994485",
    "goodreads_rating": "3",
    "goodreads_exclusive_shelf": "read",
    "goodreads_date_read": "2016-12-21",
    "goodreads_date_added": "2016-12-19",
    "goodreads_binding": "Kindle Edition",
    "goodreads_pages": "126",
    "goodreads_publication_year": "2012",
    "goodreads_original_publication_year": "1818"
  },
  {
    "id": "book-dune",
    "title": "Dune (Dune, #1)",
    "date": "2017-02-02",
    "slug": "book-dune",
    "book_status": "rated",
    "original_source": "Goodreads",
    "book_author": "Frank Herbert",
    "goodreads_book_id": "11323604",
    "goodreads_rating": "4",
    "goodreads_exclusive_shelf": "read",
    "goodreads_date_read": "2017-02-02",
    "goodreads_date_added": "2014-10-21",
    "goodreads_publisher": "Gateway",
    "goodreads_binding": "ebook",
    "goodreads_pages": "680",
    "goodreads_publication_year": "2010",
    "goodreads_original_publication_year": "1965"
  },
  {
    "id": "book-the-sense-of-an-ending",
    "title": "The Sense of an Ending",
    "date": "2017-02-08",
    "slug": "book-the-sense-of-an-ending",
    "book_status": "rated",
    "original_source": "Goodreads",
    "book_author": "Julian Barnes",
    "goodreads_book_id": "12168283",
    "goodreads_rating": "4",
    "goodreads_exclusive_shelf": "read",
    "goodreads_date_read": "2017-02-08",
    "goodreads_date_added": "2017-02-02",
    "goodreads_publisher": "Vintage Digital",
    "goodreads_binding": "Kindle Edition",
    "goodreads_pages": "151",
    "goodreads_publication_year": "2011",
    "goodreads_original_publication_year": "2011"
  },
  {
    "id": "book-i-wrote-this-for-you",
    "title": "I Wrote This For You (I Wrote This For You #4)",
    "date": "2017-04-06",
    "slug": "book-i-wrote-this-for-you",
    "book_status": "rated",
    "original_source": "Goodreads",
    "book_author": "pleasefindthis",
    "goodreads_book_id": "13105527",
    "goodreads_rating": "4",
    "goodreads_exclusive_shelf": "read",
    "goodreads_date_read": "2017-04-06",
    "goodreads_date_added": "2016-09-19",
    "goodreads_isbn": "1926760689",
    "goodreads_isbn13": "9781926760681",
    "goodreads_publisher": "Central Avenue Publishing",
    "goodreads_binding": "Paperback",
    "goodreads_pages": "194",
    "goodreads_publication_year": "2011",
    "goodreads_original_publication_year": "2011"
  },
  {
    "id": "book-the-lord-of-the-rings",
    "title": "The Lord of the Rings",
    "date": "2017-05-13",
    "slug": "book-the-lord-of-the-rings",
    "book_status": "rated",
    "original_source": "Goodreads",
    "book_author": "J.R.R. Tolkien",
    "goodreads_book_id": "11047557",
    "goodreads_rating": "5",
    "goodreads_exclusive_shelf": "read",
    "goodreads_date_read": "2017-05-13",
    "goodreads_date_added": "2017-02-11",
    "goodreads_publisher": "HarperCollins",
    "goodreads_binding": "ebook",
    "goodreads_pages": "1209",
    "goodreads_publication_year": "2009",
    "goodreads_original_publication_year": "1959"
  },
  {
    "id": "book-the-vegetarian",
    "title": "The Vegetarian",
    "date": "2017-05-19",
    "slug": "book-the-vegetarian",
    "book_status": "rated",
    "original_source": "Goodreads",
    "book_author": "Han Kang",
    "goodreads_book_id": "24377476",
    "goodreads_rating": "2",
    "goodreads_exclusive_shelf": "read",
    "goodreads_date_read": "2017-05-19",
    "goodreads_date_added": "2017-05-13",
    "goodreads_isbn": "1846275636",
    "goodreads_isbn13": "9781846275630",
    "goodreads_publisher": "Granta Books",
    "goodreads_binding": "Kindle Edition",
    "goodreads_pages": "192",
    "goodreads_publication_year": "2015",
    "goodreads_original_publication_year": "2007"
  },
  {
    "id": "book-all-quiet-on-the-western-front",
    "title": "All Quiet on the Western Front",
    "date": "2017-05-27",
    "slug": "book-all-quiet-on-the-western-front",
    "book_status": "rated",
    "original_source": "Goodreads",
    "book_author": "Erich Maria Remarque",
    "goodreads_book_id": "11223446",
    "goodreads_rating": "5",
    "goodreads_exclusive_shelf": "read",
    "goodreads_date_read": "2017-05-27",
    "goodreads_date_added": "2014-07-05",
    "goodreads_publisher": "Vintage Digital",
    "goodreads_binding": "ebook",
    "goodreads_pages": "224",
    "goodreads_publication_year": "2010",
    "goodreads_original_publication_year": "1928"
  },
  {
    "id": "book-strange-case-of-dr-jekyll-and-mr-hyde",
    "title": "Strange Case of Dr. Jekyll and Mr. Hyde",
    "date": "2017-08-16",
    "slug": "book-strange-case-of-dr-jekyll-and-mr-hyde",
    "book_status": "rated",
    "original_source": "Goodreads",
    "book_author": "Robert Louis Stevenson",
    "goodreads_book_id": "27864998",
    "goodreads_rating": "3",
    "goodreads_exclusive_shelf": "read",
    "goodreads_date_read": "2017-08-16",
    "goodreads_date_added": "2017-08-16",
    "goodreads_isbn": "9176370577",
    "goodreads_isbn13": "9789176370575",
    "goodreads_publisher": "Wisehouse Classics",
    "goodreads_binding": "Kindle Edition",
    "goodreads_pages": "88",
    "goodreads_publication_year": "2019",
    "goodreads_original_publication_year": "1886"
  },
  {
    "id": "book-the-emperor-s-soul",
    "title": "The Emperor's Soul",
    "date": "2017-08-18",
    "slug": "book-the-emperor-s-soul",
    "book_status": "rated",
    "original_source": "Goodreads",
    "book_author": "Brandon Sanderson",
    "goodreads_book_id": "17213238",
    "goodreads_rating": "5",
    "goodreads_exclusive_shelf": "read",
    "goodreads_date_read": "2017-08-18",
    "goodreads_date_added": "2016-12-22",
    "goodreads_publisher": "Gollancz",
    "goodreads_binding": "Kindle Edition",
    "goodreads_pages": "110",
    "goodreads_publication_year": "2013",
    "goodreads_original_publication_year": "2012"
  },
  {
    "id": "book-equal-rites",
    "title": "Equal Rites (Discworld, #3; Witches, #1)",
    "date": "2017-08-24",
    "slug": "book-equal-rites",
    "book_status": "rated",
    "original_source": "Goodreads",
    "book_author": "Terry Pratchett",
    "goodreads_book_id": "6567830",
    "goodreads_rating": "4",
    "goodreads_exclusive_shelf": "read",
    "goodreads_date_read": "2017-08-24",
    "goodreads_date_added": "2017-08-24",
    "goodreads_isbn": "0061804835",
    "goodreads_isbn13": "9780061804830",
    "goodreads_publisher": "HarperCollins e-books",
    "goodreads_binding": "Kindle Edition",
    "goodreads_pages": "277",
    "goodreads_publication_year": "2009",
    "goodreads_original_publication_year": "1987"
  },
  {
    "id": "book-mort",
    "title": "Mort (Discworld, #4)",
    "date": "2017-09-30",
    "slug": "book-mort",
    "book_status": "rated",
    "original_source": "Goodreads",
    "book_author": "Terry Pratchett",
    "goodreads_book_id": "8862633",
    "goodreads_rating": "5",
    "goodreads_exclusive_shelf": "read",
    "goodreads_date_read": "2017-09-30",
    "goodreads_date_added": "2017-09-30",
    "goodreads_publisher": "HarperCollins e-books",
    "goodreads_binding": "ebook",
    "goodreads_pages": "309",
    "goodreads_publication_year": "2009",
    "goodreads_original_publication_year": "1987"
  },
  {
    "id": "book-delhi-a-novel",
    "title": "Delhi: A Novel",
    "date": "2017-10-30",
    "slug": "book-delhi-a-novel",
    "book_status": "rated",
    "original_source": "Goodreads",
    "book_author": "Khushwant Singh",
    "goodreads_book_id": "34872983",
    "goodreads_rating": "2",
    "goodreads_exclusive_shelf": "read",
    "goodreads_date_read": "2017-10-30",
    "goodreads_date_added": "2017-10-30",
    "goodreads_publisher": "Penguin",
    "goodreads_binding": "Kindle Edition",
    "goodreads_pages": "405",
    "goodreads_publication_year": "2016",
    "goodreads_original_publication_year": "1990"
  },
  {
    "id": "book-do-androids-dream-of-electric-sheep",
    "title": "Do Androids Dream of Electric Sheep?",
    "date": "2017-11-05",
    "slug": "book-do-androids-dream-of-electric-sheep",
    "book_status": "rated",
    "original_source": "Goodreads",
    "book_author": "Philip K. Dick",
    "goodreads_book_id": "7082",
    "goodreads_rating": "4",
    "goodreads_exclusive_shelf": "read",
    "goodreads_date_read": "2017-11-05",
    "goodreads_date_added": "2014-11-10",
    "goodreads_publisher": "Del Rey / Ballantine Books",
    "goodreads_binding": "Paperback",
    "goodreads_pages": "244",
    "goodreads_publication_year": "1996",
    "goodreads_original_publication_year": "1968"
  },
  {
    "id": "book-man-s-search-for-meaning",
    "title": "Man's Search for Meaning",
    "date": "2017-11-05",
    "slug": "book-man-s-search-for-meaning",
    "book_status": "rated",
    "original_source": "Goodreads",
    "book_author": "Viktor E. Frankl",
    "goodreads_book_id": "19306508",
    "goodreads_rating": "5",
    "goodreads_exclusive_shelf": "read",
    "goodreads_date_read": "2017-11-05",
    "goodreads_date_added": "2016-06-01",
    "goodreads_publisher": "Ebury Digital",
    "goodreads_binding": "Kindle Edition",
    "goodreads_pages": "229",
    "goodreads_publication_year": "2013",
    "goodreads_original_publication_year": "1946"
  },
  {
    "id": "book-the-end-of-india",
    "title": "The End of India",
    "date": "2017-11-14",
    "slug": "book-the-end-of-india",
    "book_status": "rated",
    "original_source": "Goodreads",
    "book_author": "Khushwant Singh",
    "goodreads_book_id": "34872984",
    "goodreads_rating": "3",
    "goodreads_exclusive_shelf": "read",
    "goodreads_date_read": "2017-11-14",
    "goodreads_date_added": "2017-11-14",
    "goodreads_publisher": "Penguin",
    "goodreads_binding": "Kindle Edition",
    "goodreads_pages": "177",
    "goodreads_publication_year": "2017",
    "goodreads_original_publication_year": "2003"
  },
  {
    "id": "book-the-forever-war",
    "title": "The Forever War",
    "date": "2017-12-10",
    "slug": "book-the-forever-war",
    "book_status": "rated",
    "original_source": "Goodreads",
    "book_author": "Joe Haldeman",
    "goodreads_book_id": "13343065",
    "goodreads_rating": "4",
    "goodreads_exclusive_shelf": "read",
    "goodreads_date_read": "2017-12-10",
    "goodreads_date_added": "2014-10-21",
    "goodreads_isbn": "0575111445",
    "goodreads_isbn13": "9780575111448",
    "goodreads_publisher": "Gollancz",
    "goodreads_binding": "Kindle Edition",
    "goodreads_pages": "278",
    "goodreads_publication_year": "2011",
    "goodreads_original_publication_year": "1974"
  },
  {
    "id": "book-mossad",
    "title": "Mossad",
    "date": "2017-12-13",
    "slug": "book-mossad",
    "book_status": "rated",
    "original_source": "Goodreads",
    "book_author": "Michael Bar-Zohar",
    "goodreads_book_id": "29630849",
    "goodreads_rating": "5",
    "goodreads_exclusive_shelf": "read",
    "goodreads_date_read": "2017-12-13",
    "goodreads_date_added": "2017-12-13",
    "goodreads_publisher": "Jaico Publishing House",
    "goodreads_binding": "Kindle Edition",
    "goodreads_pages": "402",
    "goodreads_publication_year": "2016",
    "goodreads_original_publication_year": "2010"
  },
  {
    "id": "book-perfume-the-story-of-a-murderer",
    "title": "Perfume: The Story of a Murderer",
    "date": "2017-12-17",
    "slug": "book-perfume-the-story-of-a-murderer",
    "book_status": "rated",
    "original_source": "Goodreads",
    "book_author": "Patrick Süskind",
    "goodreads_book_id": "25697806",
    "goodreads_rating": "4",
    "goodreads_exclusive_shelf": "read",
    "goodreads_date_read": "2017-12-17",
    "goodreads_date_added": "2017-12-13",
    "goodreads_isbn": "0241975328",
    "goodreads_isbn13": "9780241975329",
    "goodreads_publisher": "Penguin Books Ltd",
    "goodreads_binding": "Kindle Edition",
    "goodreads_pages": "272",
    "goodreads_publication_year": "2015",
    "goodreads_original_publication_year": "1985"
  },
  {
    "id": "book-the-name-of-the-wind",
    "title": "The Name of the Wind (The Kingkiller Chronicle, #1)",
    "date": "2017-12-19",
    "slug": "book-the-name-of-the-wind",
    "book_status": "rated",
    "original_source": "Goodreads",
    "book_author": "Patrick Rothfuss",
    "goodreads_book_id": "11127294",
    "goodreads_rating": "3",
    "goodreads_exclusive_shelf": "read",
    "goodreads_date_read": "2017-12-19",
    "goodreads_date_added": "2014-11-10",
    "goodreads_publisher": "Gollancz",
    "goodreads_binding": "Kindle Edition",
    "goodreads_pages": "676",
    "goodreads_publication_year": "2010",
    "goodreads_original_publication_year": "2007"
  },
  {
    "id": "book-the-three-body-problem",
    "title": "The Three-Body Problem (Remembrance of Earth’s Past, #1)",
    "date": "2017-12-28",
    "slug": "book-the-three-body-problem",
    "book_status": "rated",
    "original_source": "Goodreads",
    "book_author": "Liu Cixin",
    "goodreads_book_id": "24856109",
    "goodreads_rating": "5",
    "goodreads_exclusive_shelf": "read",
    "goodreads_date_read": "2017-12-28",
    "goodreads_date_added": "2016-12-21",
    "goodreads_isbn": "1784971545",
    "goodreads_isbn13": "9781784971540",
    "goodreads_publisher": "Head of Zeus",
    "goodreads_binding": "Kindle Edition",
    "goodreads_pages": "400",
    "goodreads_publication_year": "2015",
    "goodreads_original_publication_year": "2006"
  },
  {
    "id": "book-the-company-of-women",
    "title": "The Company of Women",
    "date": "2018-04-28",
    "slug": "book-the-company-of-women",
    "book_status": "rated",
    "original_source": "Goodreads",
    "book_author": "Khushwant Singh",
    "goodreads_book_id": "34821790",
    "goodreads_rating": "3",
    "goodreads_exclusive_shelf": "read",
    "goodreads_date_read": "2018-04-28",
    "goodreads_date_added": "2018-04-28",
    "goodreads_isbn": "8184753268",
    "goodreads_publisher": "Penguin",
    "goodreads_binding": "Kindle Edition",
    "goodreads_pages": "340",
    "goodreads_publication_year": "2016",
    "goodreads_original_publication_year": "1999"
  },
  {
    "id": "book-winter-dreams",
    "title": "Winter Dreams",
    "date": "2018-06-13",
    "slug": "book-winter-dreams",
    "book_status": "rated",
    "original_source": "Goodreads",
    "book_author": "F. Scott Fitzgerald",
    "goodreads_book_id": "815356",
    "goodreads_rating": "5",
    "goodreads_exclusive_shelf": "read",
    "goodreads_date_read": "2018-06-13",
    "goodreads_date_added": "2018-06-13",
    "goodreads_isbn": "1419194348",
    "goodreads_isbn13": "9781419194344",
    "goodreads_publisher": "Kessinger Pub",
    "goodreads_binding": "Paperback",
    "goodreads_pages": "48",
    "goodreads_publication_year": "2004",
    "goodreads_original_publication_year": "1922"
  },
  {
    "id": "book-eleanor-park",
    "title": "Eleanor \u0026 Park",
    "date": "2018-06-26",
    "slug": "book-eleanor-park",
    "book_status": "rated",
    "original_source": "Goodreads",
    "book_author": "Rainbow Rowell",
    "goodreads_book_id": "17617613",
    "goodreads_rating": "5",
    "goodreads_exclusive_shelf": "read",
    "goodreads_date_read": "2018-06-26",
    "goodreads_date_added": "2018-06-26",
    "goodreads_publisher": "Orion",
    "goodreads_binding": "Kindle Edition",
    "goodreads_pages": "329",
    "goodreads_publication_year": "2012",
    "goodreads_original_publication_year": "2012"
  },
  {
    "id": "book-interpreter-of-maladies",
    "title": "Interpreter of Maladies",
    "date": "2018-11-04",
    "slug": "book-interpreter-of-maladies",
    "book_status": "rated",
    "original_source": "Goodreads",
    "book_author": "Jhumpa Lahiri",
    "goodreads_book_id": "5439",
    "goodreads_rating": "3",
    "goodreads_exclusive_shelf": "read",
    "goodreads_date_read": "2018-11-04",
    "goodreads_date_added": "2017-05-10",
    "goodreads_isbn": "0618101365",
    "goodreads_isbn13": "9780618101368",
    "goodreads_publisher": "Houghton Mifflin Harcourt",
    "goodreads_binding": "Hardcover",
    "goodreads_pages": "198",
    "goodreads_publication_year": "2000",
    "goodreads_original_publication_year": "1999"
  },
  {
    "id": "book-shoe-dog-a-memoir-by-the-creator-of-nike",
    "title": "Shoe Dog: A Memoir by the Creator of Nike",
    "date": "2019-12-06",
    "slug": "book-shoe-dog-a-memoir-by-the-creator-of-nike",
    "book_status": "rated",
    "original_source": "Goodreads",
    "book_author": "Phil Knight",
    "goodreads_book_id": "27220736",
    "goodreads_rating": "4",
    "goodreads_exclusive_shelf": "read",
    "goodreads_date_read": "2019-12-06",
    "goodreads_date_added": "2019-12-11",
    "goodreads_isbn": "1501135910",
    "goodreads_isbn13": "9781501135910",
    "goodreads_publisher": "Scribner",
    "goodreads_binding": "Hardcover",
    "goodreads_pages": "400",
    "goodreads_publication_year": "2016",
    "goodreads_original_publication_year": "2016"
  },
  {
    "id": "book-exit-strategy",
    "title": "Exit Strategy (The Murderbot Diaries, #4)",
    "date": "2020-03-10",
    "slug": "book-exit-strategy",
    "book_status": "rated",
    "original_source": "Goodreads",
    "book_author": "Martha Wells",
    "goodreads_book_id": "35519109",
    "goodreads_rating": "3",
    "goodreads_exclusive_shelf": "read",
    "goodreads_date_read": "2020-03-10",
    "goodreads_date_added": "2020-03-09",
    "goodreads_publisher": "Tordotcom",
    "goodreads_binding": "Kindle Edition",
    "goodreads_pages": "172",
    "goodreads_publication_year": "2018",
    "goodreads_original_publication_year": "2018"
  },
  {
    "id": "book-conspirata",
    "title": "Conspirata (Cicero, #2)",
    "date": "2021-01-02",
    "slug": "book-conspirata",
    "book_status": "rated",
    "original_source": "Goodreads",
    "book_author": "Robert   Harris",
    "goodreads_book_id": "3629971",
    "goodreads_rating": "2",
    "goodreads_exclusive_shelf": "read",
    "goodreads_date_read": "2021-01-02",
    "goodreads_date_added": "2021-03-14",
    "goodreads_isbn": "0743266102",
    "goodreads_isbn13": "9780743266109",
    "goodreads_publisher": "Simon \u0026 Schuster",
    "goodreads_binding": "Hardcover",
    "goodreads_pages": "352",
    "goodreads_publication_year": "2010",
    "goodreads_original_publication_year": "2009"
  },
  {
    "id": "book-dictator",
    "title": "Dictator (Cicero, #3)",
    "date": "2021-01-20",
    "slug": "book-dictator",
    "book_status": "rated",
    "original_source": "Goodreads",
    "book_author": "Robert   Harris",
    "goodreads_book_id": "25488982",
    "goodreads_rating": "3",
    "goodreads_exclusive_shelf": "read",
    "goodreads_date_read": "2021-01-20",
    "goodreads_date_added": "2021-03-14",
    "goodreads_isbn": "0307957942",
    "goodreads_isbn13": "9780307957948",
    "goodreads_publisher": "Knopf",
    "goodreads_binding": "Hardcover",
    "goodreads_pages": "385",
    "goodreads_publication_year": "2016",
    "goodreads_original_publication_year": "2015"
  },
  {
    "id": "book-the-midnight-library",
    "title": "The Midnight Library (The Midnight World, #1)",
    "date": "2021-03-01",
    "slug": "book-the-midnight-library",
    "book_status": "rated",
    "original_source": "Goodreads",
    "book_author": "Matt Haig",
    "goodreads_book_id": "52578297",
    "goodreads_rating": "2",
    "goodreads_exclusive_shelf": "read",
    "goodreads_date_read": "2021-03-01",
    "goodreads_date_added": "2020-12-22",
    "goodreads_isbn": "0525559477",
    "goodreads_isbn13": "9780525559474",
    "goodreads_publisher": "Viking",
    "goodreads_binding": "Hardcover",
    "goodreads_pages": "288",
    "goodreads_publication_year": "2020",
    "goodreads_original_publication_year": "2020"
  },
  {
    "id": "book-the-housekeeper-and-the-professor",
    "title": "The Housekeeper and the Professor",
    "date": "2021-04-03",
    "slug": "book-the-housekeeper-and-the-professor",
    "book_status": "rated",
    "original_source": "Goodreads",
    "book_author": "Yōko Ogawa",
    "goodreads_book_id": "3181564",
    "goodreads_rating": "3",
    "goodreads_exclusive_shelf": "read",
    "goodreads_date_read": "2021-04-03",
    "goodreads_date_added": "2020-12-18",
    "goodreads_isbn": "0312427808",
    "goodreads_isbn13": "9780312427801",
    "goodreads_publisher": "Picador",
    "goodreads_binding": "Paperback",
    "goodreads_pages": "180",
    "goodreads_publication_year": "2009",
    "goodreads_original_publication_year": "2005"
  },
  {
    "id": "book-we-have-always-lived-in-the-castle",
    "title": "We Have Always Lived in the Castle",
    "date": "2021-05-17",
    "slug": "book-we-have-always-lived-in-the-castle",
    "book_status": "rated",
    "original_source": "Goodreads",
    "book_author": "Shirley Jackson",
    "goodreads_book_id": "89724",
    "goodreads_rating": "1",
    "goodreads_exclusive_shelf": "read",
    "goodreads_date_added": "2021-05-17",
    "goodreads_isbn": "0143039970",
    "goodreads_isbn13": "9780143039976",
    "goodreads_publisher": "Penguin Books",
    "goodreads_binding": "Paperback",
    "goodreads_pages": "152",
    "goodreads_publication_year": "2006",
    "goodreads_original_publication_year": "1962"
  },
  {
    "id": "book-project-hail-mary",
    "title": "Project Hail Mary",
    "date": "2021-12-28",
    "slug": "book-project-hail-mary",
    "book_status": "rated",
    "original_source": "Goodreads",
    "book_author": "Andy Weir",
    "goodreads_book_id": "54493401",
    "goodreads_rating": "3",
    "goodreads_exclusive_shelf": "read",
    "goodreads_date_read": "2021-12-28",
    "goodreads_date_added": "2021-08-02",
    "goodreads_isbn": "0593135202",
    "goodreads_isbn13": "9780593135204",
    "goodreads_publisher": "Ballantine Books",
    "goodreads_binding": "Hardcover",
    "goodreads_pages": "476",
    "goodreads_publication_year": "2021",
    "goodreads_original_publication_year": "2021"
  },
  {
    "id": "book-into-thin-air-a-personal-account-of-the-mt-everest-disaster",
    "title": "Into Thin Air: A Personal Account of the Mt. Everest Disaster",
    "date": "2021-12-31",
    "slug": "book-into-thin-air-a-personal-account-of-the-mt-everest-disaster",
    "book_status": "rated",
    "original_source": "Goodreads",
    "book_author": "Jon Krakauer",
    "goodreads_book_id": "1898",
    "goodreads_rating": "5",
    "goodreads_exclusive_shelf": "read",
    "goodreads_date_read": "2021-12-31",
    "goodreads_date_added": "2021-12-31",
    "goodreads_publisher": "Anchor Books",
    "goodreads_binding": "Paperback",
    "goodreads_pages": "368",
    "goodreads_publication_year": "1999",
    "goodreads_original_publication_year": "1997"
  },
  {
    "id": "book-ghachar-ghochar",
    "title": "Ghachar Ghochar",
    "date": "2022-01-02",
    "slug": "book-ghachar-ghochar",
    "book_status": "rated",
    "original_source": "Goodreads",
    "book_author": "Vivek Shanbhag",
    "goodreads_book_id": "30267604",
    "goodreads_rating": "5",
    "goodreads_exclusive_shelf": "read",
    "goodreads_date_read": "2022-01-02",
    "goodreads_date_added": "2022-01-02",
    "goodreads_isbn": "014311168X",
    "goodreads_isbn13": "9780143111689",
    "goodreads_publisher": "Penguin Books",
    "goodreads_binding": "Paperback",
    "goodreads_pages": "118",
    "goodreads_publication_year": "2017",
    "goodreads_original_publication_year": "2013"
  },
  {
    "id": "book-looking-for-alaska",
    "title": "Looking for Alaska",
    "date": "2022-01-02",
    "slug": "book-looking-for-alaska",
    "book_status": "rated",
    "original_source": "Goodreads",
    "book_author": "John Green",
    "goodreads_book_id": "99561",
    "goodreads_rating": "1",
    "goodreads_exclusive_shelf": "read",
    "goodreads_date_read": "2022-01-02",
    "goodreads_date_added": "2022-01-02",
    "goodreads_isbn": "1435249151",
    "goodreads_isbn13": "9781435249158",
    "goodreads_publisher": "Speak",
    "goodreads_binding": "Paperback",
    "goodreads_pages": "221",
    "goodreads_publication_year": "2006",
    "goodreads_original_publication_year": "2005"
  },
  {
    "id": "book-truck-de-india-a-hitchhiker-s-guide-to-hindustan",
    "title": "Truck de India!: A Hitchhiker's Guide to Hindustan",
    "date": "2022-01-13",
    "slug": "book-truck-de-india-a-hitchhiker-s-guide-to-hindustan",
    "book_status": "rated",
    "original_source": "Goodreads",
    "book_author": "Rajat Ubhaykar",
    "goodreads_book_id": "50840378",
    "goodreads_rating": "4",
    "goodreads_exclusive_shelf": "read",
    "goodreads_date_read": "2022-01-13",
    "goodreads_date_added": "2022-01-13",
    "goodreads_isbn": "938679764X",
    "goodreads_isbn13": "9789386797643",
    "goodreads_publisher": "Simon \u0026 Schuster India",
    "goodreads_binding": "Paperback",
    "goodreads_pages": "309",
    "goodreads_publication_year": "2019"
  },
  {
    "id": "book-goat-days",
    "title": "Goat Days",
    "date": "2022-01-30",
    "slug": "book-goat-days",
    "book_status": "rated",
    "original_source": "Goodreads",
    "book_author": "Benyamin",
    "goodreads_book_id": "15849749",
    "goodreads_rating": "2",
    "goodreads_exclusive_shelf": "read",
    "goodreads_date_read": "2022-01-30",
    "goodreads_date_added": "2022-01-30",
    "goodreads_isbn": "0143416332",
    "goodreads_isbn13": "9780143416333",
    "goodreads_publisher": "Penguin Books",
    "goodreads_binding": "Paperback",
    "goodreads_pages": "255",
    "goodreads_publication_year": "2012",
    "goodreads_original_publication_year": "2008"
  },
  {
    "id": "book-the-girl-with-the-dragon-tattoo",
    "title": "The Girl With the Dragon Tattoo (Millennium, #1)",
    "date": "2022-03-18",
    "slug": "book-the-girl-with-the-dragon-tattoo",
    "book_status": "rated",
    "original_source": "Goodreads",
    "book_author": "Stieg Larsson",
    "goodreads_book_id": "2429135",
    "goodreads_rating": "3",
    "goodreads_exclusive_shelf": "read",
    "goodreads_date_read": "2022-03-18",
    "goodreads_date_added": "2022-03-17",
    "goodreads_isbn": "0670069019",
    "goodreads_isbn13": "9780670069019",
    "goodreads_publisher": "Viking Canada",
    "goodreads_binding": "Hardcover",
    "goodreads_pages": "480",
    "goodreads_publication_year": "2008",
    "goodreads_original_publication_year": "2005"
  },
  {
    "id": "book-the-white-tiger",
    "title": "The White Tiger",
    "date": "2022-03-29",
    "slug": "book-the-white-tiger",
    "book_status": "rated",
    "original_source": "Goodreads",
    "book_author": "Aravind Adiga",
    "goodreads_book_id": "6012393",
    "goodreads_rating": "4",
    "goodreads_exclusive_shelf": "read",
    "goodreads_date_read": "2022-03-29",
    "goodreads_date_added": "2015-01-13",
    "goodreads_isbn": "1843547228",
    "goodreads_isbn13": "9781843547228",
    "goodreads_publisher": "Atlantic",
    "goodreads_binding": "Paperback",
    "goodreads_pages": "321",
    "goodreads_publication_year": "2009",
    "goodreads_original_publication_year": "2008"
  },
  {
    "id": "book-convenience-store-woman",
    "title": "Convenience Store Woman",
    "date": "2022-04-04",
    "slug": "book-convenience-store-woman",
    "book_status": "rated",
    "original_source": "Goodreads",
    "book_author": "Sayaka Murata",
    "goodreads_book_id": "38357895",
    "goodreads_rating": "3",
    "goodreads_exclusive_shelf": "read",
    "goodreads_date_read": "2022-04-04",
    "goodreads_date_added": "2022-04-03",
    "goodreads_publisher": "Portobello Books",
    "goodreads_binding": "Paperback",
    "goodreads_pages": "163",
    "goodreads_publication_year": "2018",
    "goodreads_original_publication_year": "2016"
  },
  {
    "id": "book-the-seven-husbands-of-evelyn-hugo",
    "title": "The Seven Husbands of Evelyn Hugo",
    "date": "2022-04-23",
    "slug": "book-the-seven-husbands-of-evelyn-hugo",
    "book_status": "rated",
    "original_source": "Goodreads",
    "book_author": "Taylor Jenkins Reid",
    "goodreads_book_id": "32620332",
    "goodreads_rating": "4",
    "goodreads_exclusive_shelf": "read",
    "goodreads_date_read": "2022-04-23",
    "goodreads_date_added": "2019-02-13",
    "goodreads_isbn": "1501139231",
    "goodreads_isbn13": "9781501139239",
    "goodreads_publisher": "Atria Books",
    "goodreads_binding": "Hardcover",
    "goodreads_pages": "389",
    "goodreads_publication_year": "2017",
    "goodreads_original_publication_year": "2017"
  },
  {
    "id": "book-milk-and-honey",
    "title": "Milk and honey",
    "date": "2022-04-25",
    "slug": "book-milk-and-honey",
    "book_status": "rated",
    "original_source": "Goodreads",
    "book_author": "Rupi Kaur",
    "goodreads_book_id": "23513349",
    "goodreads_rating": "2",
    "goodreads_exclusive_shelf": "read",
    "goodreads_date_added": "2022-04-25",
    "goodreads_isbn": "1502784270",
    "goodreads_isbn13": "9781502784278",
    "goodreads_publisher": "Createspace Independent Pub",
    "goodreads_binding": "Paperback",
    "goodreads_pages": "204",
    "goodreads_publication_year": "2014",
    "goodreads_original_publication_year": "2014"
  },
  {
    "id": "book-unaccustomed-earth",
    "title": "Unaccustomed Earth",
    "date": "2022-05-19",
    "slug": "book-unaccustomed-earth",
    "book_status": "rated",
    "original_source": "Goodreads",
    "book_author": "Jhumpa Lahiri",
    "goodreads_book_id": "85301",
    "goodreads_rating": "5",
    "goodreads_exclusive_shelf": "read",
    "goodreads_date_read": "2022-05-19",
    "goodreads_date_added": "2022-05-20",
    "goodreads_isbn": "0676979343",
    "goodreads_isbn13": "9780676979343",
    "goodreads_publisher": "Knopf",
    "goodreads_binding": "Hardcover",
    "goodreads_pages": "352",
    "goodreads_publication_year": "2008",
    "goodreads_original_publication_year": "2008"
  },
  {
    "id": "book-the-house-in-the-cerulean-sea",
    "title": "The House in the Cerulean Sea (Cerulean Chronicles, #1)",
    "date": "2022-10-15",
    "slug": "book-the-house-in-the-cerulean-sea",
    "book_status": "rated",
    "original_source": "Goodreads",
    "book_author": "T.J. Klune",
    "goodreads_book_id": "45047384",
    "goodreads_rating": "5",
    "goodreads_exclusive_shelf": "read",
    "goodreads_date_read": "2022-10-15",
    "goodreads_date_added": "2021-06-12",
    "goodreads_publisher": "Tor Books",
    "goodreads_binding": "Kindle Edition",
    "goodreads_pages": "394",
    "goodreads_publication_year": "2020",
    "goodreads_original_publication_year": "2020"
  },
  {
    "id": "book-the-ocean-at-the-end-of-the-lane",
    "title": "The Ocean at the End of the Lane",
    "date": "2022-12-27",
    "slug": "book-the-ocean-at-the-end-of-the-lane",
    "book_status": "rated",
    "original_source": "Goodreads",
    "book_author": "Neil Gaiman",
    "goodreads_book_id": "15783514",
    "goodreads_rating": "3",
    "goodreads_exclusive_shelf": "read",
    "goodreads_date_read": "2022-12-27",
    "goodreads_date_added": "2022-12-27",
    "goodreads_isbn": "0062255657",
    "goodreads_isbn13": "9780062255655",
    "goodreads_publisher": "William Morrow Books",
    "goodreads_binding": "Hardcover",
    "goodreads_pages": "181",
    "goodreads_publication_year": "2013",
    "goodreads_original_publication_year": "2013"
  },
  {
    "id": "book-the-poisonwood-bible",
    "title": "The Poisonwood Bible",
    "date": "2023-02-01",
    "slug": "book-the-poisonwood-bible",
    "book_status": "rated",
    "original_source": "Goodreads",
    "book_author": "Barbara Kingsolver",
    "goodreads_book_id": "7244",
    "goodreads_rating": "4",
    "goodreads_exclusive_shelf": "read",
    "goodreads_date_read": "2023-02-01",
    "goodreads_date_added": "2023-02-12",
    "goodreads_isbn": "0060786507",
    "goodreads_isbn13": "9780060786502",
    "goodreads_publisher": "Harper Perennial Modern Classics",
    "goodreads_binding": "Paperback",
    "goodreads_pages": "546",
    "goodreads_publication_year": "2005",
    "goodreads_original_publication_year": "1998"
  },
  {
    "id": "book-the-glass-palace",
    "title": "The Glass Palace",
    "date": "2023-03-24",
    "slug": "book-the-glass-palace",
    "book_status": "rated",
    "original_source": "Goodreads",
    "book_author": "Amitav Ghosh",
    "goodreads_book_id": "77103",
    "goodreads_rating": "5",
    "goodreads_exclusive_shelf": "read",
    "goodreads_date_read": "2023-03-24",
    "goodreads_date_added": "2023-02-12",
    "goodreads_isbn": "0375758771",
    "goodreads_isbn13": "9780375758775",
    "goodreads_publisher": "Random House Trade Paperbacks",
    "goodreads_binding": "Paperback",
    "goodreads_pages": "486",
    "goodreads_publication_year": "2002",
    "goodreads_original_publication_year": "2000"
  },
  {
    "id": "book-lonesome-dove",
    "title": "Lonesome Dove (Lonesome Dove, #1)",
    "date": "2023-08-08",
    "slug": "book-lonesome-dove",
    "book_status": "rated",
    "original_source": "Goodreads",
    "book_author": "Larry McMurtry",
    "goodreads_book_id": "256008",
    "goodreads_rating": "4",
    "goodreads_exclusive_shelf": "read",
    "goodreads_date_read": "2023-08-08",
    "goodreads_date_added": "2022-12-28",
    "goodreads_isbn": "067168390X",
    "goodreads_isbn13": "9780671683900",
    "goodreads_publisher": "Pocket Books",
    "goodreads_binding": "Mass Market Paperback",
    "goodreads_pages": "960",
    "goodreads_publication_year": "1999",
    "goodreads_original_publication_year": "1985"
  },
  {
    "id": "book-hourglass-time-memory-marriage",
    "title": "Hourglass: Time, Memory, Marriage",
    "date": "2024-02-01",
    "slug": "book-hourglass-time-memory-marriage",
    "book_status": "rated",
    "original_source": "Goodreads",
    "book_author": "Dani Shapiro",
    "goodreads_book_id": "31522007",
    "goodreads_rating": "5",
    "goodreads_exclusive_shelf": "read",
    "goodreads_date_read": "2024-02-01",
    "goodreads_date_added": "2021-06-12",
    "goodreads_isbn": "0451494482",
    "goodreads_isbn13": "9780451494481",
    "goodreads_publisher": "Knopf",
    "goodreads_binding": "Hardcover",
    "goodreads_pages": "160",
    "goodreads_publication_year": "2017",
    "goodreads_original_publication_year": "2017"
  },
  {
    "id": "book-i-who-have-never-known-men",
    "title": "I Who Have Never Known Men",
    "date": "2024-07-27",
    "slug": "book-i-who-have-never-known-men",
    "book_status": "rated",
    "original_source": "Goodreads",
    "book_author": "Jacqueline Harpman",
    "goodreads_book_id": "11996",
    "goodreads_rating": "2",
    "goodreads_exclusive_shelf": "read",
    "goodreads_date_added": "2024-07-27",
    "goodreads_isbn": "0380731819",
    "goodreads_isbn13": "9780380731817",
    "goodreads_publisher": "Avon Eos",
    "goodreads_binding": "Mass Market Paperback",
    "goodreads_pages": "208",
    "goodreads_publication_year": "1998",
    "goodreads_original_publication_year": "1995"
  },
  {
    "id": "book-blindsight",
    "title": "Blindsight (Firefall, #1)",
    "date": "2024-09-28",
    "slug": "book-blindsight",
    "book_status": "rated",
    "original_source": "Goodreads",
    "book_author": "Peter Watts",
    "goodreads_book_id": "48484",
    "goodreads_rating": "3",
    "goodreads_exclusive_shelf": "read",
    "goodreads_date_read": "2024-09-28",
    "goodreads_date_added": "2024-08-02",
    "goodreads_isbn": "0765312182",
    "goodreads_isbn13": "9780765312181",
    "goodreads_publisher": "Tor Books",
    "goodreads_binding": "Hardcover",
    "goodreads_pages": "384",
    "goodreads_publication_year": "2006",
    "goodreads_original_publication_year": "2006"
  },
  {
    "id": "book-tales-from-the-cafe",
    "title": "Tales from the Cafe (Before the Coffee Gets Cold, #2)",
    "date": "2025-01-16",
    "slug": "book-tales-from-the-cafe",
    "book_status": "rated",
    "original_source": "Goodreads",
    "book_author": "Toshikazu Kawaguchi",
    "goodreads_book_id": "54373691",
    "goodreads_rating": "4",
    "goodreads_exclusive_shelf": "read",
    "goodreads_date_read": "2025-01-16",
    "goodreads_date_added": "2025-01-16",
    "goodreads_isbn": "1529050863",
    "goodreads_isbn13": "9781529050868",
    "goodreads_publisher": "Picador",
    "goodreads_binding": "Paperback",
    "goodreads_pages": "192",
    "goodreads_publication_year": "2020",
    "goodreads_original_publication_year": "2017"
  },
  {
    "id": "book-before-the-coffee-gets-cold",
    "title": "Before the Coffee Gets Cold (Before the Coffee Gets Cold, #1)",
    "date": "2025-03-01",
    "slug": "book-before-the-coffee-gets-cold",
    "book_status": "rated",
    "original_source": "Goodreads",
    "book_author": "Toshikazu Kawaguchi",
    "goodreads_book_id": "44421460",
    "goodreads_rating": "3",
    "goodreads_exclusive_shelf": "read",
    "goodreads_date_read": "2025-03-01",
    "goodreads_date_added": "2021-08-08",
    "goodreads_isbn": "1529029589",
    "goodreads_isbn13": "9781529029581",
    "goodreads_publisher": "Picador",
    "goodreads_binding": "Paperback",
    "goodreads_pages": "213",
    "goodreads_publication_year": "2019",
    "goodreads_original_publication_year": "2015"
  },
  {
    "id": "book-i-m-glad-my-mom-died",
    "title": "I'm Glad My Mom Died",
    "date": "2025-03-01",
    "slug": "book-i-m-glad-my-mom-died",
    "book_status": "rated",
    "original_source": "Goodreads",
    "book_author": "Jennette McCurdy",
    "goodreads_book_id": "59366244",
    "goodreads_rating": "4",
    "goodreads_exclusive_shelf": "read",
    "goodreads_date_read": "2025-03-01",
    "goodreads_date_added": "2025-03-20",
    "goodreads_isbn": "1982185821",
    "goodreads_isbn13": "9781982185824",
    "goodreads_publisher": "Simon \u0026 Schuster",
    "goodreads_binding": "Hardcover",
    "goodreads_pages": "304",
    "goodreads_publication_year": "2022",
    "goodreads_original_publication_year": "2022"
  },
  {
    "id": "book-liars",
    "title": "Liars",
    "date": "2025-03-01",
    "slug": "book-liars",
    "book_status": "rated",
    "original_source": "Goodreads",
    "book_author": "Sarah Manguso",
    "goodreads_book_id": "200556722",
    "goodreads_rating": "4",
    "goodreads_exclusive_shelf": "read",
    "goodreads_date_read": "2025-03-01",
    "goodreads_date_added": "2024-08-01",
    "goodreads_isbn": "0593241266",
    "goodreads_isbn13": "9780593241264",
    "goodreads_publisher": "Hogarth",
    "goodreads_binding": "Kindle Edition",
    "goodreads_pages": "260",
    "goodreads_publication_year": "2024",
    "goodreads_original_publication_year": "2024"
  },
  {
    "id": "book-the-nvidia-way-jensen-huang-and-the-making-of-a-tech-giant",
    "title": "The Nvidia Way: Jensen Huang and the Making of a Tech Giant",
    "date": "2025-04-13",
    "slug": "book-the-nvidia-way-jensen-huang-and-the-making-of-a-tech-giant",
    "book_status": "rated",
    "original_source": "Goodreads",
    "book_author": "Tae   Kim",
    "goodreads_book_id": "218319936",
    "goodreads_rating": "5",
    "goodreads_exclusive_shelf": "read",
    "goodreads_date_added": "2025-04-13",
    "goodreads_isbn": "1324086726",
    "goodreads_isbn13": "9781324086727",
    "goodreads_publisher": "W. W. Norton \u0026 Company",
    "goodreads_binding": "Kindle Edition",
    "goodreads_pages": "268",
    "goodreads_publication_year": "2024"
  },
  {
    "id": "book-apple-in-china-the-capture-of-the-world-s-greatest-company",
    "title": "Apple in China: The Capture of the World's Greatest Company",
    "date": "2025-06-17",
    "slug": "book-apple-in-china-the-capture-of-the-world-s-greatest-company",
    "book_status": "rated",
    "original_source": "Goodreads",
    "book_author": "Patrick  McGee",
    "goodreads_book_id": "220161058",
    "goodreads_rating": "5",
    "goodreads_exclusive_shelf": "read",
    "goodreads_date_added": "2025-06-17",
    "goodreads_isbn": "1668053373",
    "goodreads_isbn13": "9781668053379",
    "goodreads_publisher": "Scribner",
    "goodreads_binding": "Hardcover",
    "goodreads_pages": "448",
    "goodreads_publication_year": "2025",
    "goodreads_original_publication_year": "2025"
  },
  {
    "id": "book-brotherless-night",
    "title": "Brotherless Night",
    "date": "2025-09-26",
    "slug": "book-brotherless-night",
    "book_status": "rated",
    "original_source": "Goodreads",
    "book_author": "V.V. Ganeshananthan",
    "goodreads_book_id": "60324341",
    "goodreads_rating": "5",
    "goodreads_exclusive_shelf": "read",
    "goodreads_date_read": "2025-09-26",
    "goodreads_date_added": "2025-07-14",
    "goodreads_isbn": "0812997158",
    "goodreads_isbn13": "9780812997156",
    "goodreads_publisher": "Random House",
    "goodreads_binding": "Hardcover",
    "goodreads_pages": "348",
    "goodreads_publication_year": "2023",
    "goodreads_original_publication_year": "2023"
  }
]
